LICENSE
MANIFEST.in
README.rst
setup.cfg
setup.py
django_kp_html_meta.egg-info/PKG-INFO
django_kp_html_meta.egg-info/SOURCES.txt
django_kp_html_meta.egg-info/dependency_links.txt
django_kp_html_meta.egg-info/top_level.txt
kp_html_meta/__init__.py
kp_html_meta/admin.py
kp_html_meta/apps.py
kp_html_meta/models.py
kp_html_meta/tests.py
kp_html_meta/views.py
kp_html_meta/locale/fr/LC_MESSAGES/django.mo
kp_html_meta/locale/fr/LC_MESSAGES/django.po
kp_html_meta/migrations/__init__.py
kp_html_meta/templates/kp_meta/meta.html
kp_html_meta/templatetags/__init__.py
kp_html_meta/templatetags/kp_meta.py