Metadata-Version: 1.1
Name: django-kp-html-meta
Version: 0.1
Summary: kp_html_meta is a Django app to generate html meta tags for improve SEO.
Home-page: https://github.com/KernelPan1k/django-kp-html-meta
Author: kernel-panik
Author-email: UNKNOWN
License: GPLv3
Platform: UNKNOWN
Classifier: Environment :: Web Environment
Classifier: Framework :: Django
Classifier: Intended Audience :: Developers
Classifier: License :: OSI Approved :: GNU General Public License v3 (GPLv3)
Classifier: Operating System :: OS Independent
Classifier: Programming Language :: Python
Classifier: Programming Language :: Python :: 2
Classifier: Programming Language :: Python :: 3
Classifier: Topic :: Internet :: WWW/HTTP
Classifier: Topic :: Internet :: WWW/HTTP :: Dynamic Content
